data_request_client/__init__.py
data_request_client/_exceptions.py
data_request_client/auth.py
data_request_client/client.py
data_request_client/logging.py
data_request_client/models.py
data_request_client/settings.py
data_request_client/utils.py
data_request_client-0.7.1.dist-info/METADATA
data_request_client-0.7.1.dist-info/WHEEL
data_request_client-0.7.1.dist-info/RECORD
