Metadata-Version: 2.1
Name: data-request-client
Version: 0.7.1
Summary: 
Author: Michael Statt
Author-email: michael.statt@modelyst.io
Requires-Python: >=3.10,<4.0
Classifier: Programming Language :: Python :: 3
Classifier: Programming Language :: Python :: 3.10
Classifier: Programming Language :: Python :: 3.11
Classifier: Programming Language :: Python :: 3.12
Requires-Dist: boto3 (>=1.28.52,<2.0.0)
Requires-Dist: httpx (>=0.25.0,<0.26.0)
Requires-Dist: pydantic-settings (>=2.0.3,<3.0.0)
